metapyrodigal/load_balancer.py
metapyrodigal/main.py
metapyrodigal/orf_finder.py
metapyrodigal/utils.py
metapyrodigal-1.4.1.dist-info/LICENSE
metapyrodigal-1.4.1.dist-info/METADATA
metapyrodigal-1.4.1.dist-info/WHEEL
metapyrodigal-1.4.1.dist-info/entry_points.txt
metapyrodigal-1.4.1.dist-info/top_level.txt
metapyrodigal-1.4.1.dist-info/RECORD
