Metadata-Version: 2.2
Name: metapyrodigal
Version: 1.4.1
Summary: Pyrodigal cli optimized for metagenomic data
Author-email: Cody Martin <codycmar10@gmail.com>
License: MIT License
Project-URL: Homepage, https://github.com/cody-mar10/metapyrodigal
Project-URL: Bug Tracker, https://github.com/cody-mar10/metapyrodigal/issues
Classifier: Programming Language :: Python :: 3
Classifier: License :: OSI Approved :: MIT License
Requires-Python: >=3.10
License-File: LICENSE
Requires-Dist: pyrodigal==3.5.2
Requires-Dist: tqdm>=4.42
Requires-Dist: pyrodigal-gv
Requires-Dist: pyfastatools>=2.3
